Finch/__init__.py
Finch/generic.py
Finch/prompt_maker.py
Finch/rates.py
Finch/selectors.py
Finch/universal.py
Finch/layers/__init__.py
Finch/layers/array_layers.py
Finch/layers/float_arrays.py
Finch/layers/image_layers.py
Finch/layers/string_layers.py
Finch/layers/universal_layers.py
finch_genetics-3.5.3.dist-info/METADATA
finch_genetics-3.5.3.dist-info/WHEEL
finch_genetics-3.5.3.dist-info/top_level.txt
finch_genetics-3.5.3.dist-info/RECORD
