Metadata-Version: 2.1
Name: finch-genetics
Version: 3.5.3
Summary: A flexible framework for evolutionary algorithms in Python
Home-page: https://github.com/dadukhankevin/Finch
Author: Daniel Losey
Author-email: danieljlosey@gmail.com
Classifier: Development Status :: 3 - Alpha
Classifier: Intended Audience :: Developers
Classifier: Intended Audience :: Science/Research
Classifier: License :: OSI Approved :: MIT License
Classifier: Operating System :: OS Independent
Classifier: Programming Language :: Python :: 3
Classifier: Programming Language :: Python :: 3.7
Classifier: Programming Language :: Python :: 3.8
Classifier: Programming Language :: Python :: 3.9
Classifier: Programming Language :: Python :: 3.10
Classifier: Programming Language :: Python :: 3.11
Classifier: Programming Language :: Python :: 3.12
Classifier: Topic :: Scientific/Engineering :: Artificial Intelligence
Requires-Python: >=3.7
Requires-Dist: numpy >=1.18.0
Requires-Dist: matplotlib >=3.1.0
Requires-Dist: pillow >=7.0.0
Provides-Extra: gpu
Requires-Dist: cupy >=7.0.0 ; extra == 'gpu'
